{
    "euler001": {
        "score": 60, 
        "timestamp": 41559342
    }, 
    "euler002": {
        "score": 100, 
        "timestamp": 41609295
    }, 
    "euler003": {
        "score": 66, 
        "timestamp": 41755346
    }, 
    "euler004": {
        "score": 0, 
        "timestamp": 0
    }, 
    "euler005": {
        "score": 75, 
        "timestamp": 42055380
    }, 
    "euler006": {
        "score": 100, 
        "timestamp": 42059527
    }, 
    "euler007": {
        "score": 0, 
        "timestamp": 0
    }
}