{
    "euler001": {
        "score": 100, 
        "timestamp": 107921083
    }, 
    "euler002": {
        "score": 100, 
        "timestamp": 107922219
    }, 
    "euler003": {
        "score": 100, 
        "timestamp": 107987205
    }, 
    "euler004": {
        "score": 100, 
        "timestamp": 107964139
    }, 
    "euler005": {
        "score": 100, 
        "timestamp": 107966486
    }, 
    "euler006": {
        "score": 100, 
        "timestamp": 107987846
    }, 
    "euler007": {
        "score": 100, 
        "timestamp": 108085105
    }, 
    "euler008": {
        "score": 100, 
        "timestamp": 108081050
    }, 
    "euler009": {
        "score": 100, 
        "timestamp": 108000836
    }, 
    "euler010": {
        "score": 100, 
        "timestamp": 108081419
    }, 
    "euler011": {
        "score": 100, 
        "timestamp": 108692301
    }, 
    "euler012": {
        "score": 100, 
        "timestamp": 108693890
    }, 
    "euler013": {
        "score": 100, 
        "timestamp": 108011854
    }, 
    "euler014": {
        "score": 100, 
        "timestamp": 108871283
    }, 
    "euler015": {
        "score": 100, 
        "timestamp": 108088389
    }, 
    "euler016": {
        "score": 100, 
        "timestamp": 108079806
    }, 
    "euler017": {
        "score": 100, 
        "timestamp": 108080335
    }, 
    "euler018": {
        "score": 100, 
        "timestamp": 108327485
    }, 
    "euler019": {
        "score": 100, 
        "timestamp": 108871168
    }, 
    "euler020": {
        "score": 100, 
        "timestamp": 108401598
    }, 
    "euler021": {
        "score": 100, 
        "timestamp": 108498511
    }, 
    "euler022": {
        "score": 100, 
        "timestamp": 108871092
    }, 
    "euler023": {
        "score": 100, 
        "timestamp": 108495956
    }, 
    "euler024": {
        "score": 100, 
        "timestamp": 108511682
    }, 
    "euler025": {
        "score": 100, 
        "timestamp": 108870957
    }, 
    "euler026": {
        "score": 100, 
        "timestamp": 108870687
    }, 
    "euler027": {
        "score": 100, 
        "timestamp": 108867443
    }, 
    "euler028": {
        "score": 100, 
        "timestamp": 108869686
    }, 
    "euler030": {
        "score": 100, 
        "timestamp": 109034674
    }, 
    "euler031": {
        "score": 100, 
        "timestamp": 109044278
    }, 
    "euler032": {
        "score": 100, 
        "timestamp": 109044923
    }, 
    "euler034": {
        "score": 100, 
        "timestamp": 109046415
    }, 
    "euler035": {
        "score": 100, 
        "timestamp": 109135425
    }, 
    "euler036": {
        "score": 100, 
        "timestamp": 108939020
    }, 
    "euler037": {
        "score": 100, 
        "timestamp": 109033934
    }, 
    "euler038": {
        "score": 100, 
        "timestamp": 109225399
    }, 
    "euler039": {
        "score": 100, 
        "timestamp": 109135867
    }, 
    "euler040": {
        "score": 100, 
        "timestamp": 109136485
    }, 
    "euler041": {
        "score": 100, 
        "timestamp": 109136220
    }, 
    "euler042": {
        "score": 100, 
        "timestamp": 109136946
    }, 
    "euler043": {
        "score": 100, 
        "timestamp": 109137052
    }, 
    "euler044": {
        "score": 100, 
        "timestamp": 109137460
    }, 
    "euler045": {
        "score": 100, 
        "timestamp": 109224369
    }, 
    "euler046": {
        "score": 100, 
        "timestamp": 109224659
    }, 
    "euler047": {
        "score": 100, 
        "timestamp": 109224963
    }, 
    "euler049": {
        "score": 0, 
        "timestamp": 0
    }, 
    "euler051": {
        "score": 100, 
        "timestamp": 109314281
    }, 
    "euler052": {
        "score": 100, 
        "timestamp": 109314059
    }, 
    "euler055": {
        "score": 100, 
        "timestamp": 109314794
    }, 
    "euler057": {
        "score": 100, 
        "timestamp": 109313802
    }, 
    "euler059": {
        "score": 66, 
        "timestamp": 109313635
    }, 
    "euler067": {
        "score": 100, 
        "timestamp": 109225698
    }, 
    "euler197": {
        "score": 0, 
        "timestamp": 0
    }
}